Workbook

Sheet Pila de Producto (Backlog)
B1: Desarrollo ágil: Pila de Producto (Product Backlog) — consolidada en 4 sprints por fases operativas y dependencias
B3: Orden de ejecución | C3: Identificador (ID) de la Historia | D3: Enunciado de la Historia | E3: Alias | F3: Estado | G3: Puntos Valor | H3: Puntos Historia | I3: ROI | J3: Iteración (Sprint) | K3: Prioridad | L3: Depende de | M3: Comentarios
B4: 1 | C4: h2 | D4: Como Administrador (Don Ludo), quiero abrir una nueva sesión nocturna seleccionando la fecha con detección automática del día de la semana, para habilitar las operaciones de venta y arqueo de la fecha. | E4: Apertura de Sesión | F4: Completada | G4: 8 | H4: 3 | I4: =ROUND(G4/H4,2) -> 2.67 | J4: Sprint 1 | K4: ALTA | L4: {=INDEX('Plan de Sprints'!$I$13:$I$29,MATCH(C4,'Plan de Sprints'!$D$13:$D$29,0))} -> — | M4: Habilitador principal para iniciar toda la operación de la noche.
B5: 2 | C5: h11 | D5: Como Administrador, quiero modificar el stock de bodega con botones de pasos (-10, -1, +1, +10) o edición directa con guardado automático, para registrar entradas y mermas en segundos sin recargar la página. | E5: Ajuste Stock Bodega | F5: Completada | G5: 6 | H5: 5 | I5: =ROUND(G5/H5,2) -> 1.2 | J5: Sprint 1 | K5: MEDIA | L5: {=INDEX('Plan de Sprints'!$I$13:$I$29,MATCH(C5,'Plan de Sprints'!$D$13:$D$29,0))} -> — | M5: Interfaz ágil para ajustar mermas o ingresos rápidos de stock.
B6: 3 | C6: h12 | D6: Como Bartender o Administrador, quiero registrar las cajas y botellas que se suben de la bodega central a cada barra al inicio del turno, para fijar el stock de apertura por punto de despacho. | E6: Despacho a Barras | F6: Completada | G6: 7 | H6: 5 | I6: =ROUND(G6/H6,2) -> 1.4 | J6: Sprint 1 | K6: MEDIA | L6: {=INDEX('Plan de Sprints'!$I$13:$I$29,MATCH(C6,'Plan de Sprints'!$D$13:$D$29,0))} -> h11, h2 | M6: Control preciso de transferencia interna de insumos bodega-barra.
B7: 4 | C7: h15 | D7: Como Administrador (Don Ludo), quiero gestionar la nómina de trabajadores con su nombre, celular, cargo normalizado (MESERO, BARTENDER, SEGURIDAD, LIMPIEZA) y jornal habitual, para tener la plantilla centralizada. | E7: Maestro de Personal | F7: Completada | G7: 6 | H7: 5 | I7: =ROUND(G7/H7,2) -> 1.2 | J7: Sprint 1 | K7: MEDIA | L7: {=INDEX('Plan de Sprints'!$I$13:$I$29,MATCH(C7,'Plan de Sprints'!$D$13:$D$29,0))} -> — | M7: Mantenimiento centralizado de la base de datos de trabajadores.
B8: 5 | C8: h14 | D8: Como Cajero o Mesero, quiero registrar cobros por QR seleccionando Yasta o Yape con sus logos oficiales e indicando el monto, para registrar transferencias bancarias de forma intuitiva. | E8: Cobros QR | F8: Completada | G8: 8 | H8: 3 | I8: =ROUND(G8/H8,2) -> 2.67 | J8: Sprint 2 | K8: ALTA | L8: {=INDEX('Plan de Sprints'!$I$13:$I$29,MATCH(C8,'Plan de Sprints'!$D$13:$D$29,0))} -> h2 | M8: Agiliza el registro visual de cobros digitales en barra y caja.
B9: 6 | C9: h13 | D9: Como Administrador (Don Ludo), quiero que al ingresar el voucher de tarjeta el sistema calcule la retención de la comisión del banco y el monto neto real que ingresa a la cuenta bancaria, para conocer la liquidez real. | E9: Retención de Tarjetas | F9: Completada | G9: 7 | H9: 4 | I9: =ROUND(G9/H9,2) -> 1.75 | J9: Sprint 2 | K9: MEDIA | L9: {=INDEX('Plan de Sprints'!$I$13:$I$29,MATCH(C9,'Plan de Sprints'!$D$13:$D$29,0))} -> h2 | M9: Proporciona la cifra real neta en banco deduciendo comisiones.
B10: 7 | C10: h6 | D10: Como Administrador, quiero que al abrir la noche se cargue automáticamente la nómina del personal programado para ese día con su jornal pactado, para liquidar los pagos del turno sin reescribir la lista. | E10: Carga Nómina Diaria | F10: Planificada | G10: 7 | H10: 5 | I10: =ROUND(G10/H10,2) -> 1.4 | J10: Sprint 2 | K10: MEDIA | L10: {=INDEX('Plan de Sprints'!$I$13:$I$29,MATCH(C10,'Plan de Sprints'!$D$13:$D$29,0))} -> h2, h15 | M10: Precarga el equipo de trabajo evitando reescritura de planillas.
B11: 8 | C11: h4 | D11: Como Administrador, quiero registrar el conteo de botellas sobrantes al final de la noche en cada barra para que el sistema calcule automáticamente los combos vendidos y botellas extra, para determinar las ventas reales. | E11: Conteo Botellas/Combos | F11: Planificada | G11: 9 | H11: 8 | I11: =ROUND(G11/H11,2) -> 1.13 | J11: Sprint 2 | K11: ALTA | L11: {=INDEX('Plan de Sprints'!$I$13:$I$29,MATCH(C11,'Plan de Sprints'!$D$13:$D$29,0))} -> h12, h2 | M11: Requiere lógica de conversión de consumos frente a inventario físico.
B12: 9 | C12: h5 | D12: Como Administrador (Don Ludo), quiero ver en un solo cuadro el total vendido en bebidas, lo cobrado por QR, lo tarjeteado y el efectivo neto que debe entregar cada bartender, para liquidar el turno sin diferencias. | E12: Liquidación por Turno | F12: Planificada | G12: 10 | H12: 3 | I12: =ROUND(G12/H12,2) -> 3.33 | J12: Sprint 3 | K12: ALTA | L12: {=INDEX('Plan de Sprints'!$I$13:$I$29,MATCH(C12,'Plan de Sprints'!$D$13:$D$29,0))} -> h4, h13, h14, h6 | M12: Vital para conciliación rápida y prevención de faltantes al cierre de caja.
B13: 10 | C13: h3 | D13: Como Encargado de Barra, quiero sincronizar el inventario de apertura copiando automáticamente los saldos finales de la noche anterior, para no tener que recontar ni digitar de nuevo el stock base. | E13: Stock Inicial Barra | F13: Planificada | G13: 9 | H13: 5 | I13: =ROUND(G13/H13,2) -> 1.8 | J13: Sprint 3 | K13: ALTA | L13: {=INDEX('Plan de Sprints'!$I$13:$I$29,MATCH(C13,'Plan de Sprints'!$D$13:$D$29,0))} -> h4, h12 | M13: Automatiza la carga inicial evitando recuentos manuales innecesarios.
B14: 11 | C14: h16 | D14: Como Administrador (Don Ludo), quiero marcar como pagado o editar el jornal de un trabajador con recálculo matemático inmediato de la planilla en el DOM, para pagar al personal en efectivo con rapidez. | E14: Pago Rápido Personal | F14: Planificada | G14: 8 | H14: 5 | I14: =ROUND(G14/H14,2) -> 1.6 | J14: Sprint 3 | K14: MEDIA | L14: {=INDEX('Plan de Sprints'!$I$13:$I$29,MATCH(C14,'Plan de Sprints'!$D$13:$D$29,0))} -> h6, h15 | M14: Agiliza el pago de sueldos en efectivo al finalizar la jornada.
B15: 12 | C15: h17 | D15: Como Administrador, quiero pagar el jornal atrasado a un trabajador pulsando 'Pagar Jornal' con liquidación asincrónica instantánea, para saldar deudas de noches pasadas sin recargar la página. | E15: Pago Deudas Atrasadas | F15: Planificada | G15: 6 | H15: 8 | I15: =ROUND(G15/H15,2) -> 0.75 | J15: Sprint 3 | K15: BAJA | L15: {=INDEX('Plan de Sprints'!$I$13:$I$29,MATCH(C15,'Plan de Sprints'!$D$13:$D$29,0))} -> h16, h15 | M15: Gestión asíncrona de liquidación de pasivos de fechas anteriores.
... B20: 17 | C20: h10 | D20: Como Administrador de Bodega, quiero alternar entre una vista de Tabla Ejecutiva y una Cuadrícula de Tarjetas táctiles, para agilizar tanto el conteo rápido de más de 30 marcas como la auditoría visual. | E20: Vista Táctil Bodega | F20: Planificada | G20: 5 | H20: 8 | I20: =ROUND(G20/H20,2) -> 0.63 | J20: Sprint 4 | K20: BAJA | L20: {=INDEX('Plan de Sprints'!$I$13:$I$29,MATCH(C20,'Plan de Sprints'!$D$13:$D$29,0))} -> h11 | M20: Componente UI dual para auditoría táctil y rápida en bodega.
B22: Estado sigue el instructivo de la plantilla PMO Informática: 'Planificada' = asignada a un sprint y sin iniciar. Puntos, prioridad y comentarios son los del archivo v3; el color de cada fila indica su sprint.

Sheet Plan de Sprints
B1: Plan de Sprints por fases operativas y dependencias (4 sprints)
B3: Sprint | C3: Fase operativa y objetivo | D3: N° Historias | E3: Puntos Historia | F3: Puntos Valor | G3: ROI del Sprint
B4: Sprint 1 | C4: Datos maestros, apertura de sesión e inventario inicial: Cargar personal y stock de bodega, abrir una nueva noche y fijar el stock de apertura de cada barra. | D4: =COUNTIF('Pila de Producto (Backlog)'!$J$4:$J$20,B4) -> 4 | E4: =SUMIF('Pila de Producto (Backlog)'!$J$4:$J$20,B4,'Pila de Producto (Backlog)'!$H$4:$H$20) -> 18 | F4: =SUMIF('Pila de Producto (Backlog)'!$J$4:$J$20,B4,'Pila de Producto (Backlog)'!$G$4:$G$20) -> 27 | G4: =IF(E4=0,0,ROUND(F4/E4,2)) -> 1.5
B5: Sprint 2 | C5: Configuración del turno y ventas en vivo: Precargar la nómina del día, registrar cobros por QR y tarjeta y calcular las ventas reales de cada barra con el conteo de cierre. | D5: =COUNTIF('Pila de Producto (Backlog)'!$J$4:$J$20,B5) -> 4 | E5: =SUMIF('Pila de Producto (Backlog)'!$J$4:$J$20,B5,'Pila de Producto (Backlog)'!$H$4:$H$20) -> 20 | F5: =SUMIF('Pila de Producto (Backlog)'!$J$4:$J$20,B5,'Pila de Producto (Backlog)'!$G$4:$G$20) -> 31 | G5: =IF(E5=0,0,ROUND(F5/E5,2)) -> 1.55
B6: Sprint 3 | C6: Liquidación, pagos y cierres operativos: Liquidar cada turno, pagar al personal (incluidos jornales atrasados) y dejar los saldos finales listos como stock de la noche siguiente. | D6: =COUNTIF('Pila de Producto (Backlog)'!$J$4:$J$20,B6) -> 4 | E6: =SUMIF('Pila de Producto (Backlog)'!$J$4:$J$20,B6,'Pila de Producto (Backlog)'!$H$4:$H$20) -> 21 | F6: =SUMIF('Pila de Producto (Backlog)'!$J$4:$J$20,B6,'Pila de Producto (Backlog)'!$G$4:$G$20) -> 33 | G6: =IF(E6=0,0,ROUND(F6/E6,2)) -> 1.57
B7: Sprint 4 | C7: Balance final, arqueo y dashboard: Balance ingresos vs egresos, arqueo del efectivo físico, dashboard ejecutivo, sellado seguro de la noche y vista táctil de bodega (diferible). | D7: =COUNTIF('Pila de Producto (Backlog)'!$J$4:$J$20,B7) -> 5 | E7: =SUMIF('Pila de Producto (Backlog)'!$J$4:$J$20,B7,'Pila de Producto (Backlog)'!$H$4:$H$20) -> 20 | F7: =SUMIF('Pila de Producto (Backlog)'!$J$4:$J$20,B7,'Pila de Producto (Backlog)'!$G$4:$G$20) -> 40 | G7: =IF(E7=0,0,ROUND(F7/E7,2)) -> 2
B8: Total | D8: =SUM(D4:D7) -> 17 | E8: =SUM(E4:E7) -> 79 | F8: =SUM(F4:F7) -> 131 | G8: =IF(E8=0,0,ROUND(F8/E8,2)) -> 1.66
B11: Orden de ejecución y dependencias | L11: Auxiliares: IDs de las dependencias (única fuente de 'Depende de')
B12: Orden | C12: Alias | D12: ID | E12: Sprint anterior (5 sprints) | F12: Sprint nuevo | G12: Puntos Historia | H12: ROI | I12: Depende de | J12: Motivo del orden | K12: Validación de dependencias | L12: Dep. 1 | M12: Dep. 2 | N12: Dep. 3 | O12: Dep. 4 | P12: Dep. 5 | Q12: Dep. 6
B13: 1 | C13: {=INDEX('Pila de Producto (Backlog)'!$E$4:$E$20,MATCH($D13,'Pila de Producto (Backlog)'!$C$4:$C$20,0))} -> Apertura de Sesión | D13: h2 | E13: Sprint 1 | F13: {=INDEX('Pila de Producto (Backlog)'!$J$4:$J$20,MATCH($D13,'Pila de Producto (Backlog)'!$C$4:$C$20,0))} -> Sprint 1 | G13: {=INDEX('Pila de Producto (Backlog)'!$H$4:$H$20,MATCH($D13,'Pila de Producto (Backlog)'!$C$4:$C$20,0))} -> 3 | H13: {=INDEX('Pila de Producto (Backlog)'!$I$4:$I$20,MATCH($D13,'Pila de Producto (Backlog)'!$C$4:$C$20,0))} -> 2.67 | I13: =IF(COUNTA(L13:Q13)=0,"—",L13&IF(M13<>"",", "&M13,"")&IF(N13<>"",", "&N13,"")&IF(O13<>"",", "&O13,"")&IF(P13<>"",", "&P13,"")&IF(Q13<>"",", "&Q13,"")) -> — | J13: Habilita toda la operación de la noche: sin sesión abierta no hay stock de turno, cobros, ventas ni arqueo. | K13: {=IF(COUNTA(L13:Q13)=0,"OK (sin dependencias)",IF(SUMPRODUCT((L13:Q13<>"")*(COUNTIF($D$13:$D$29,L13:Q13)=0))>0,"ERROR: ID no existe",IF(MAX(IFERROR(INDEX($B$13:$B$29,MATCH(L13,$D$13:$D$29,0)),0),IFERROR(INDEX($B$13:$B$29,MATCH(M13,$D$13:$D$29,0)),0),IFERROR(INDEX($B$13:$B$29,MATCH(N13,$D$13:$D$29,0)),0),IFERROR(INDEX($B$13:$B$29,MATCH(O13,$D$13:$D$29,0)),0),IFERROR(INDEX($B$13:$B$29,MATCH(P13,$D$13:$D$29,0)),0),IFERROR(INDEX($B$13:$B$29,MATCH(Q13,$D$13:$D$29,0)),0))<B13,"OK","ERROR: depende de una historia posterior")))} -> OK (sin dependencias)
B14: 2 | C14: {=INDEX('Pila de Producto (Backlog)'!$E$4:$E$20,MATCH($D14,'Pila de Producto (Backlog)'!$C$4:$C$20,0))} -> Ajuste Stock Bodega | D14: h11 | E14: Sprint 1 | F14: {=INDEX('Pila de Producto (Backlog)'!$J$4:$J$20,MATCH($D14,'Pila de Producto (Backlog)'!$C$4:$C$20,0))} -> Sprint 1 | G14: {=INDEX('Pila de Producto (Backlog)'!$H$4:$H$20,MATCH($D14,'Pila de Producto (Backlog)'!$C$4:$C$20,0))} -> 5 | H14: {=INDEX('Pila de Producto (Backlog)'!$I$4:$I$20,MATCH($D14,'Pila de Producto (Backlog)'!$C$4:$C$20,0))} -> 1.2 | I14: =IF(COUNTA(L14:Q14)=0,"—",L14&IF(M14<>"",", "&M14,"")&IF(N14<>"",", "&N14,"")&IF(O14<>"",", "&O14,"")&IF(P14<>"",", "&P14,"")&IF(Q14<>"",", "&Q14,"")) -> — | J14: Dato maestro del stock de bodega; h12 y h10 parten de él. | K14: {=IF(COUNTA(L14:Q14)=0,"OK (sin dependencias)",IF(SUMPRODUCT((L14:Q14<>"")*(COUNTIF($D$13:$D$29,L14:Q14)=0))>0,"ERROR: ID no existe",IF(MAX(IFERROR(INDEX($B$13:$B$29,MATCH(L14,$D$13:$D$29,0)),0),IFERROR(INDEX($B$13:$B$29,MATCH(M14,$D$13:$D$29,0)),0),IFERROR(INDEX($B$13:$B$29,MATCH(N14,$D$13:$D$29,0)),0),IFERROR(INDEX($B$13:$B$29,MATCH(O14,$D$13:$D$29,0)),0),IFERROR(INDEX($B$13:$B$29,MATCH(P14,$D$13:$D$29,0)),0),IFERROR(INDEX($B$13:$B$29,MATCH(Q14,$D$13:$D$29,0)),0))<B14,"OK","ERROR: depende de una historia posterior")))} -> OK (sin dependencias)
B15: 3 | C15: {=INDEX('Pila de Producto (Backlog)'!$E$4:$E$20,MATCH($D15,'Pila de Producto (Backlog)'!$C$4:$C$20,0))} -> Despacho a Barras | D15: h12 | E15: Sprint 2 | F15: {=INDEX('Pila de Producto (Backlog)'!$J$4:$J$20,MATCH($D15,'Pila de Producto (Backlog)'!$C$4:$C$20,0))} -> Sprint 1 | G15: {=INDEX('Pila de Producto (Backlog)'!$H$4:$H$20,MATCH($D15,'Pila de Producto (Backlog)'!$C$4:$C$20,0))} -> 5 | H15: {=INDEX('Pila de Producto (Backlog)'!$I$4:$I$20,MATCH($D15,'Pila de Producto (Backlog)'!$C$4:$C$20,0))} -> 1.4 | I15: =IF(COUNTA(L15:Q15)=0,"—",L15&IF(M15<>"",", "&M15,"")&IF(N15<>"",", "&N15,"")&IF(O15<>"",", "&O15,"")&IF(P15<>"",", "&P15,"")&IF(Q15<>"",", "&Q15,"")) -> h11, h2 | J15: Fija el stock de apertura de cada barra con lo que sale de bodega; h4 y h3 parten de este dato. Cubre también el stock de apertura de la primera noche. | K15: {=IF(COUNTA(L15:Q15)=0,"OK (sin dependencias)",IF(SUMPRODUCT((L15:Q15<>"")*(COUNTIF($D$13:$D$29,L15:Q15)=0))>0,"ERROR: ID no existe",IF(MAX(IFERROR(INDEX($B$13:$B$29,MATCH(L15,$D$13:$D$29,0)),0),IFERROR(INDEX($B$13:$B$29,MATCH(M15,$D$13:$D$29,0)),0),IFERROR(INDEX($B$13:$B$29,MATCH(N15,$D$13:$D$29,0)),0),IFERROR(INDEX($B$13:$B$29,MATCH(O15,$D$13:$D$29,0)),0),IFERROR(INDEX($B$13:$B$29,MATCH(P15,$D$13:$D$29,0)),0),IFERROR(INDEX($B$13:$B$29,MATCH(Q15,$D$13:$D$29,0)),0))<B15,"OK","ERROR: depende de una historia posterior")))} -> OK | L15: h11 | M15: h2
B16: 4 | C16: {=INDEX('Pila de Producto (Backlog)'!$E$4:$E$20,MATCH($D16,'Pila de Producto (Backlog)'!$C$4:$C$20,0))} -> Maestro de Personal | D16: h15 | E16: Sprint 1 | F16: {=INDEX('Pila de Producto (Backlog)'!$J$4:$J$20,MATCH($D16,'Pila de Producto (Backlog)'!$C$4:$C$20,0))} -> Sprint 1 | G16: {=INDEX('Pila de Producto (Backlog)'!$H$4:$H$20,MATCH($D16,'Pila de Producto (Backlog)'!$C$4:$C$20,0))} -> 5 | H16: {=INDEX('Pila de Producto (Backlog)'!$I$4:$I$20,MATCH($D16,'Pila de Producto (Backlog)'!$C$4:$C$20,0))} -> 1.2 | I16: =IF(COUNTA(L16:Q16)=0,"—",L16&IF(M16<>"",", "&M16,"")&IF(N16<>"",", "&N16,"")&IF(O16<>"",", "&O16,"")&IF(P16<>"",", "&P16,"")&IF(Q16<>"",", "&Q16,"")) -> — | J16: Dato maestro de trabajadores; h6, h16 y h17 lo usan. | K16: {=IF(COUNTA(L16:Q16)=0,"OK (sin dependencias)",IF(SUMPRODUCT((L16:Q16<>"")*(COUNTIF($D$13:$D$29,L16:Q16)=0))>0,"ERROR: ID no existe",IF(MAX(IFERROR(INDEX($B$13:$B$29,MATCH(L16,$D$13:$D$29,0)),0),IFERROR(INDEX($B$13:$B$29,MATCH(M16,$D$13:$D$29,0)),0),IFERROR(INDEX($B$13:$B$29,MATCH(N16,$D$13:$D$29,0)),0),IFERROR(INDEX($B$13:$B$29,MATCH(O16,$D$13:$D$29,0)),0),IFERROR(INDEX($B$13:$B$29,MATCH(P16,$D$13:$D$29,0)),0),IFERROR(INDEX($B$13:$B$29,MATCH(Q16,$D$13:$D$29,0)),0))<B16,"OK","ERROR: depende de una historia posterior")))} -> OK (sin dependencias)
B17: 5 | C17: {=INDEX('Pila de Producto (Backlog)'!$E$4:$E$20,MATCH($D17,'Pila de Producto (Backlog)'!$C$4:$C$20,0))} -> Cobros QR | D17: h14 | E17: Sprint 3 | F17: {=INDEX('Pila de Producto (Backlog)'!$J$4:$J$20,MATCH($D17,'Pila de Producto (Backlog)'!$C$4:$C$20,0))} -> Sprint 2 | G17: {=INDEX('Pila de Producto (Backlog)'!$H$4:$H$20,MATCH($D17,'Pila de Producto (Backlog)'!$C$4:$C$20,0))} -> 3 | H17: {=INDEX('Pila de Producto (Backlog)'!$I$4:$I$20,MATCH($D17,'Pila de Producto (Backlog)'!$C$4:$C$20,0))} -> 2.67 | I17: =IF(COUNTA(L17:Q17)=0,"—",L17&IF(M17<>"",", "&M17,"")&IF(N17<>"",", "&N17,"")&IF(O17<>"",", "&O17,"")&IF(P17<>"",", "&P17,"")&IF(Q17<>"",", "&Q17,"")) -> h2 | J17: Registro de cobros QR durante la noche; sus montos alimentan h5, h7 y h9. | K17: {=IF(COUNTA(L17:Q17)=0,"OK (sin dependencias)",IF(SUMPRODUCT((L17:Q17<>"")*(COUNTIF($D$13:$D$29,L17:Q17)=0))>0,"ERROR: ID no existe",IF(MAX(IFERROR(INDEX($B$13:$B$29,MATCH(L17,$D$13:$D$29,0)),0),IFERROR(INDEX($B$13:$B$29,MATCH(M17,$D$13:$D$29,0)),0),IFERROR(INDEX($B$13:$B$29,MATCH(N17,$D$13:$D$29,0)),0),IFERROR(INDEX($B$13:$B$29,MATCH(O17,$D$13:$D$29,0)),0),IFERROR(INDEX($B$13:$B$29,MATCH(P17,$D$13:$D$29,0)),0),IFERROR(INDEX($B$13:$B$29,MATCH(Q17,$D$13:$D$29,0)),0))<B17,"OK","ERROR: depende de una historia posterior")))} -> OK | L17: h2
B18: 6 | C18: {=INDEX('Pila de Producto (Backlog)'!$E$4:$E$20,MATCH($D18,'Pila de Producto (Backlog)'!$C$4:$C$20,0))} -> Retención de Tarjetas | D18: h13 | E18: Sprint 3 | F18: {=INDEX('Pila de Producto (Backlog)'!$J$4:$J$20,MATCH($D18,'Pila de Producto (Backlog)'!$C$4:$C$20,0))} -> Sprint 2 | G18: {=INDEX('Pila de Producto (Backlog)'!$H$4:$H$20,MATCH($D18,'Pila de Producto (Backlog)'!$C$4:$C$20,0))} -> 4 | H18: {=INDEX('Pila de Producto (Backlog)'!$I$4:$I$20,MATCH($D18,'Pila de Producto (Backlog)'!$C$4:$C$20,0))} -> 1.75 | I18: =IF(COUNTA(L18:Q18)=0,"—",L18&IF(M18<>"",", "&M18,"")&IF(N18<>"",", "&N18,"")&IF(O18<>"",", "&O18,"")&IF(P18<>"",", "&P18,"")&IF(Q18<>"",", "&Q18,"")) -> h2 | J18: Neto real de tarjetas tras la comisión del banco; alimenta h5, h7 y h9. | K18: {=IF(COUNTA(L18:Q18)=0,"OK (sin dependencias)",IF(SUMPRODUCT((L18:Q18<>"")*(COUNTIF($D$13:$D$29,L18:Q18)=0))>0,"ERROR: ID no existe",IF(MAX(IFERROR(INDEX($B$13:$B$29,MATCH(L18,$D$13:$D$29,0)),0),IFERROR(INDEX($B$13:$B$29,MATCH(M18,$D$13:$D$29,0)),0),IFERROR(INDEX($B$13:$B$29,MATCH(N18,$D$13:$D$29,0)),0),IFERROR(INDEX($B$13:$B$29,MATCH(O18,$D$13:$D$29,0)),0),IFERROR(INDEX($B$13:$B$29,MATCH(P18,$D$13:$D$29,0)),0),IFERROR(INDEX($B$13:$B$29,MATCH(Q18,$D$13:$D$29,0)),0))<B18,"OK","ERROR: depende de una historia posterior")))} -> OK | L18: h2
B19: 7 | C19: {=INDEX('Pila de Producto (Backlog)'!$E$4:$E$20,MATCH($D19,'Pila de Producto (Backlog)'!$C$4:$C$20,0))} -> Carga Nómina Diaria | D19: h6 | E19: Sprint 2 | F19: {=INDEX('Pila de Producto (Backlog)'!$J$4:$J$20,MATCH($D19,'Pila de Producto (Backlog)'!$C$4:$C$20,0))} -> Sprint 2 | G19: {=INDEX('Pila de Producto (Backlog)'!$H$4:$H$20,MATCH($D19,'Pila de Producto (Backlog)'!$C$4:$C$20,0))} -> 5 | H19: {=INDEX('Pila de Producto (Backlog)'!$I$4:$I$20,MATCH($D19,'Pila de Producto (Backlog)'!$C$4:$C$20,0))} -> 1.4 | I19: =IF(COUNTA(L19:Q19)=0,"—",L19&IF(M19<>"",", "&M19,"")&IF(N19<>"",", "&N19,"")&IF(O19<>"",", "&O19,"")&IF(P19<>"",", "&P19,"")&IF(Q19<>"",", "&Q19,"")) -> h2, h15 | J19: Carga al abrir la noche el personal programado desde el maestro de personal; h5 y h16 la necesitan. | K19: {=IF(COUNTA(L19:Q19)=0,"OK (sin dependencias)",IF(SUMPRODUCT((L19:Q19<>"")*(COUNTIF($D$13:$D$29,L19:Q19)=0))>0,"ERROR: ID no existe",IF(MAX(IFERROR(INDEX($B$13:$B$29,MATCH(L19,$D$13:$D$29,0)),0),IFERROR(INDEX($B$13:$B$29,MATCH(M19,$D$13:$D$29,0)),0),IFERROR(INDEX($B$13:$B$29,MATCH(N19,$D$13:$D$29,0)),0),IFERROR(INDEX($B$13:$B$29,MATCH(O19,$D$13:$D$29,0)),0),IFERROR(INDEX($B$13:$B$29,MATCH(P19,$D$13:$D$29,0)),0),IFERROR(INDEX($B$13:$B$29,MATCH(Q19,$D$13:$D$29,0)),0))<B19,"OK","ERROR: depende de una historia posterior")))} -> OK | L19: h2 | M19: h15
B20: 8 | C20: {=INDEX('Pila de Producto (Backlog)'!$E$4:$E$20,MATCH($D20,'Pila de Producto (Backlog)'!$C$4:$C$20,0))} -> Conteo Botellas/Combos | D20: h4 | E20: Sprint 3 | F20: {=INDEX('Pila de Producto (Backlog)'!$J$4:$J$20,MATCH($D20,'Pila de Producto (Backlog)'!$C$4:$C$20,0))} -> Sprint 2 | G20: {=INDEX('Pila de Producto (Backlog)'!$H$4:$H$20,MATCH($D20,'Pila de Producto (Backlog)'!$C$4:$C$20,0))} -> 8 | H20: {=INDEX('Pila de Producto (Backlog)'!$I$4:$I$20,MATCH($D20,'Pila de Producto (Backlog)'!$C$4:$C$20,0))} -> 1.13 | I20: =IF(COUNTA(L20:Q20)=0,"—",L20&IF(M20<>"",", "&M20,"")&IF(N20<>"",", "&N20,"")&IF(O20<>"",", "&O20,"")&IF(P20<>"",", "&P20,"")&IF(Q20<>"",", "&Q20,"")) -> h12, h2 | J20: Convierte stock de apertura y conteo final en combos y botellas vendidas (ventas reales). Necesita h12 para conocer el stock de apertura de cada barra. | K20: {=IF(COUNTA(L20:Q20)=0,"OK (sin dependencias)",IF(SUMPRODUCT((L20:Q20<>"")*(COUNTIF($D$13:$D$29,L20:Q20)=0))>0,"ERROR: ID no existe",IF(MAX(IFERROR(INDEX($B$13:$B$29,MATCH(L20,$D$13:$D$29,0)),0),IFERROR(INDEX($B$13:$B$29,MATCH(M20,$D$13:$D$29,0)),0),IFERROR(INDEX($B$13:$B$29,MATCH(N20,$D$13:$D$29,0)),0),IFERROR(INDEX($B$13:$B$29,MATCH(O20,$D$13:$D$29,0)),0),IFERROR(INDEX($B$13:$B$29,MATCH(P20,$D$13:$D$29,0)),0),IFERROR(INDEX($B$13:$B$29,MATCH(Q20,$D$13:$D$29,0)),0))<B20,"OK","ERROR: depende de una historia posterior")))} -> OK | L20: h12 | M20: h2
B21: 9 | C21: {=INDEX('Pila de Producto (Backlog)'!$E$4:$E$20,MATCH($D21,'Pila de Producto (Backlog)'!$C$4:$C$20,0))} -> Liquidación por Turno | D21: h5 | E21: Sprint 4 | F21: {=INDEX('Pila de Producto (Backlog)'!$J$4:$J$20,MATCH($D21,'Pila de Producto (Backlog)'!$C$4:$C$20,0))} -> Sprint 3 | G21: {=INDEX('Pila de Producto (Backlog)'!$H$4:$H$20,MATCH($D21,'Pila de Producto (Backlog)'!$C$4:$C$20,0))} -> 3 | H21: {=INDEX('Pila de Producto (Backlog)'!$I$4:$I$20,MATCH($D21,'Pila de Producto (Backlog)'!$C$4:$C$20,0))} -> 3.33 | I21: =IF(COUNTA(L21:Q21)=0,"—",L21&IF(M21<>"",", "&M21,"")&IF(N21<>"",", "&N21,"")&IF(O21<>"",", "&O21,"")&IF(P21<>"",", "&P21,"")&IF(Q21<>"",", "&Q21,"")) -> h4, h13, h14, h6 | J21: Cruza lo vendido (h4) con lo cobrado por QR y tarjeta para obtener el efectivo neto por bartender; el bartender sale de la nómina del día (h6). | K21: {=IF(COUNTA(L21:Q21)=0,"OK (sin dependencias)",IF(SUMPRODUCT((L21:Q21<>"")*(COUNTIF($D$13:$D$29,L21:Q21)=0))>0,"ERROR: ID no existe",IF(MAX(IFERROR(INDEX($B$13:$B$29,MATCH(L21,$D$13:$D$29,0)),0),IFERROR(INDEX($B$13:$B$29,MATCH(M21,$D$13:$D$29,0)),0),IFERROR(INDEX($B$13:$B$29,MATCH(N21,$D$13:$D$29,0)),0),IFERROR(INDEX($B$13:$B$29,MATCH(O21,$D$13:$D$29,0)),0),IFERROR(INDEX($B$13:$B$29,MATCH(P21,$D$13:$D$29,0)),0),IFERROR(INDEX($B$13:$B$29,MATCH(Q21,$D$13:$D$29,0)),0))<B21,"OK","ERROR: depende de una historia posterior")))} -> OK | L21: h4 | M21: h13 | N21: h14 | O21: h6
B22: 10 | C22: {=INDEX('Pila de Producto (Backlog)'!$E$4:$E$20,MATCH($D22,'Pila de Producto (Backlog)'!$C$4:$C$20,0))} -> Stock Inicial Barra | D22: h3 | E22: Sprint 4 | F22: {=INDEX('Pila de Producto (Backlog)'!$J$4:$J$20,MATCH($D22,'Pila de Producto (Backlog)'!$C$4:$C$20,0))} -> Sprint 3 | G22: {=INDEX('Pila de Producto (Backlog)'!$H$4:$H$20,MATCH($D22,'Pila de Producto (Backlog)'!$C$4:$C$20,0))} -> 5 | H22: {=INDEX('Pila de Producto (Backlog)'!$I$4:$I$20,MATCH($D22,'Pila de Producto (Backlog)'!$C$4:$C$20,0))} -> 1.8 | I22: =IF(COUNTA(L22:Q22)=0,"—",L22&IF(M22<>"",", "&M22,"")&IF(N22<>"",", "&N22,"")&IF(O22<>"",", "&O22,"")&IF(P22<>"",", "&P22,"")&IF(Q22<>"",", "&Q22,"")) -> h4, h12 | J22: Copia como stock de apertura de la noche siguiente los saldos finales que produce h4; por eso va después de h4. | K22: {=IF(COUNTA(L22:Q22)=0,"OK (sin dependencias)",IF(SUMPRODUCT((L22:Q22<>"")*(COUNTIF($D$13:$D$29,L22:Q22)=0))>0,"ERROR: ID no existe",IF(MAX(IFERROR(INDEX($B$13:$B$29,MATCH(L22,$D$13:$D$29,0)),0),IFERROR(INDEX($B$13:$B$29,MATCH(M22,$D$13:$D$29,0)),0),IFERROR(INDEX($B$13:$B$29,MATCH(N22,$D$13:$D$29,0)),0),IFERROR(INDEX($B$13:$B$29,MATCH(O22,$D$13:$D$29,0)),0),IFERROR(INDEX($B$13:$B$29,MATCH(P22,$D$13:$D$29,0)),0),IFERROR(INDEX($B$13:$B$29,MATCH(Q22,$D$13:$D$29,0)),0))<B22,"OK","ERROR: depende de una historia posterior")))} -> OK | L22: h4 | M22: h12
B23: 11 | C23: {=INDEX('Pila de Producto (Backlog)'!$E$4:$E$20,MATCH($D23,'Pila de Producto (Backlog)'!$C$4:$C$20,0))} -> Pago Rápido Personal | D23: h16 | E23: Sprint 4 | F23: {=INDEX('Pila de Producto (Backlog)'!$J$4:$J$20,MATCH($D23,'Pila de Producto (Backlog)'!$C$4:$C$20,0))} -> Sprint 3 | G23: {=INDEX('Pila de Producto (Backlog)'!$H$4:$H$20,MATCH($D23,'Pila de Producto (Backlog)'!$C$4:$C$20,0))} -> 5 | H23: {=INDEX('Pila de Producto (Backlog)'!$I$4:$I$20,MATCH($D23,'Pila de Producto (Backlog)'!$C$4:$C$20,0))} -> 1.6 | I23: =IF(COUNTA(L23:Q23)=0,"—",L23&IF(M23<>"",", "&M23,"")&IF(N23<>"",", "&N23,"")&IF(O23<>"",", "&O23,"")&IF(P23<>"",", "&P23,"")&IF(Q23<>"",", "&Q23,"")) -> h6, h15 | J23: Pagar o editar el jornal requiere la nómina del día (h6) y el maestro (h15); estos pagos son egresos para h7 y h8. | K23: {=IF(COUNTA(L23:Q23)=0,"OK (sin dependencias)",IF(SUMPRODUCT((L23:Q23<>"")*(COUNTIF($D$13:$D$29,L23:Q23)=0))>0,"ERROR: ID no existe",IF(MAX(IFERROR(INDEX($B$13:$B$29,MATCH(L23,$D$13:$D$29,0)),0),IFERROR(INDEX($B$13:$B$29,MATCH(M23,$D$13:$D$29,0)),0),IFERROR(INDEX($B$13:$B$29,MATCH(N23,$D$13:$D$29,0)),0),IFERROR(INDEX($B$13:$B$29,MATCH(O23,$D$13:$D$29,0)),0),IFERROR(INDEX($B$13:$B$29,MATCH(P23,$D$13:$D$29,0)),0),IFERROR(INDEX($B$13:$B$29,MATCH(Q23,$D$13:$D$29,0)),0))<B23,"OK","ERROR: depende de una historia posterior")))} -> OK | L23: h6 | M23: h15
B24: 12 | C24: {=INDEX('Pila de Producto (Backlog)'!$E$4:$E$20,MATCH($D24,'Pila de Producto (Backlog)'!$C$4:$C$20,0))} -> Pago Deudas Atrasadas | D24: h17 | E24: Sprint 4 | F24: {=INDEX('Pila de Producto (Backlog)'!$J$4:$J$20,MATCH($D24,'Pila de Producto (Backlog)'!$C$4:$C$20,0))} -> Sprint 3 | G24: {=INDEX('Pila de Producto (Backlog)'!$H$4:$H$20,MATCH($D24,'Pila de Producto (Backlog)'!$C$4:$C$20,0))} -> 8 | H24: {=INDEX('Pila de Producto (Backlog)'!$I$4:$I$20,MATCH($D24,'Pila de Producto (Backlog)'!$C$4:$C$20,0))} -> 0.75 | I24: =IF(COUNTA(L24:Q24)=0,"—",L24&IF(M24<>"",", "&M24,"")&IF(N24<>"",", "&N24,"")&IF(O24<>"",", "&O24,"")&IF(P24<>"",", "&P24,"")&IF(Q24<>"",", "&Q24,"")) -> h16, h15 | J24: Salda jornales de noches pasadas reutilizando el flujo de pago de h16; también es egreso para h7 y h8. | K24: {=IF(COUNTA(L24:Q24)=0,"OK (sin dependencias)",IF(SUMPRODUCT((L24:Q24<>"")*(COUNTIF($D$13:$D$29,L24:Q24)=0))>0,"ERROR: ID no existe",IF(MAX(IFERROR(INDEX($B$13:$B$29,MATCH(L24,$D$13:$D$29,0)),0),IFERROR(INDEX($B$13:$B$29,MATCH(M24,$D$13:$D$29,0)),0),IFERROR(INDEX($B$13:$B$29,MATCH(N24,$D$13:$D$29,0)),0),IFERROR(INDEX($B$13:$B$29,MATCH(O24,$D$13:$D$29,0)),0),IFERROR(INDEX($B$13:$B$29,MATCH(P24,$D$13:$D$29,0)),0),IFERROR(INDEX($B$13:$B$29,MATCH(Q24,$D$13:$D$29,0)),0))<B24,"OK","ERROR: depende de una historia posterior")))} -> OK | L24: h16 | M24: h15
B25: 13 | C25: {=INDEX('Pila de Producto (Backlog)'!$E$4:$E$20,MATCH($D25,'Pila de Producto (Backlog)'!$C$4:$C$20,0))} -> Balance Express | D25: h7 | E25: Sprint 5 | F25: {=INDEX('Pila de Producto (Backlog)'!$J$4:$J$20,MATCH($D25,'Pila de Producto (Backlog)'!$C$4:$C$20,0))} -> Sprint 4 | G25: {=INDEX('Pila de Producto (Backlog)'!$H$4:$H$20,MATCH($D25,'Pila de Producto (Backlog)'!$C$4:$C$20,0))} -> 3 | H25: {=INDEX('Pila de Producto (Backlog)'!$I$4:$I$20,MATCH($D25,'Pila de Producto (Backlog)'!$C$4:$C$20,0))} -> 3.33 | I25: =IF(COUNTA(L25:Q25)=0,"—",L25&IF(M25<>"",", "&M25,"")&IF(N25<>"",", "&N25,"")&IF(O25<>"",", "&O25,"")&IF(P25<>"",", "&P25,"")&IF(Q25<>"",", "&Q25,"")) -> h13, h14, h4, h5, h16, h17 | J25: El balance ingresos vs egresos solo es real con tarjetas, QR, ventas, efectivo liquidado y pagos al personal ya registrados. | K25: {=IF(COUNTA(L25:Q25)=0,"OK (sin dependencias)",IF(SUMPRODUCT((L25:Q25<>"")*(COUNTIF($D$13:$D$29,L25:Q25)=0))>0,"ERROR: ID no existe",IF(MAX(IFERROR(INDEX($B$13:$B$29,MATCH(L25,$D$13:$D$29,0)),0),IFERROR(INDEX($B$13:$B$29,MATCH(M25,$D$13:$D$29,0)),0),IFERROR(INDEX($B$13:$B$29,MATCH(N25,$D$13:$D$29,0)),0),IFERROR(INDEX($B$13:$B$29,MATCH(O25,$D$13:$D$29,0)),0),IFERROR(INDEX($B$13:$B$29,MATCH(P25,$D$13:$D$29,0)),0),IFERROR(INDEX($B$13:$B$29,MATCH(Q25,$D$13:$D$29,0)),0))<B25,"OK","ERROR: depende de una historia posterior")))} -> OK | L25: h13 | M25: h14 | N25: h4 | O25: h5 | P25: h16 | Q25: h17
B26: 14 | C26: {=INDEX('Pila de Producto (Backlog)'!$E$4:$E$20,MATCH($D26,'Pila de Producto (Backlog)'!$C$4:$C$20,0))} -> Arqueo Efectivo Físico | D26: h8 | E26: Sprint 5 | F26: {=INDEX('Pila de Producto (Backlog)'!$J$4:$J$20,MATCH($D26,'Pila de Producto (Backlog)'!$C$4:$C$20,0))} -> Sprint 4 | G26: {=INDEX('Pila de Producto (Backlog)'!$H$4:$H$20,MATCH($D26,'Pila de Producto (Backlog)'!$C$4:$C$20,0))} -> 3 | H26: {=INDEX('Pila de Producto (Backlog)'!$I$4:$I$20,MATCH($D26,'Pila de Producto (Backlog)'!$C$4:$C$20,0))} -> 3 | I26: =IF(COUNTA(L26:Q26)=0,"—",L26&IF(M26<>"",", "&M26,"")&IF(N26<>"",", "&N26,"")&IF(O26<>"",", "&O26,"")&IF(P26<>"",", "&P26,"")&IF(Q26<>"",", "&Q26,"")) -> h5, h16, h17 | J26: Necesita el efectivo liquidado por turno (h5) y los pagos en efectivo al personal (h16, h17). | K26: {=IF(COUNTA(L26:Q26)=0,"OK (sin dependencias)",IF(SUMPRODUCT((L26:Q26<>"")*(COUNTIF($D$13:$D$29,L26:Q26)=0))>0,"ERROR: ID no existe",IF(MAX(IFERROR(INDEX($B$13:$B$29,MATCH(L26,$D$13:$D$29,0)),0),IFERROR(INDEX($B$13:$B$29,MATCH(M26,$D$13:$D$29,0)),0),IFERROR(INDEX($B$13:$B$29,MATCH(N26,$D$13:$D$29,0)),0),IFERROR(INDEX($B$13:$B$29,MATCH(O26,$D$13:$D$29,0)),0),IFERROR(INDEX($B$13:$B$29,MATCH(P26,$D$13:$D$29,0)),0),IFERROR(INDEX($B$13:$B$29,MATCH(Q26,$D$13:$D$29,0)),0))<B26,"OK","ERROR: depende de una historia posterior")))} -> OK | L26: h5 | M26: h16 | N26: h17
B27: 15 | C27: {=INDEX('Pila de Producto (Backlog)'!$E$4:$E$20,MATCH($D27,'Pila de Producto (Backlog)'!$C$4:$C$20,0))} -> Dashboard Ejecutivo | D27: h9 | E27: Sprint 5 | F27: {=INDEX('Pila de Producto (Backlog)'!$J$4:$J$20,MATCH($D27,'Pila de Producto (Backlog)'!$C$4:$C$20,0))} -> Sprint 4 | G27: {=INDEX('Pila de Producto (Backlog)'!$H$4:$H$20,MATCH($D27,'Pila de Producto (Backlog)'!$C$4:$C$20,0))} -> 3 | H27: {=INDEX('Pila de Producto (Backlog)'!$I$4:$I$20,MATCH($D27,'Pila de Producto (Backlog)'!$C$4:$C$20,0))} -> 2.67 | I27: =IF(COUNTA(L27:Q27)=0,"—",L27&IF(M27<>"",", "&M27,"")&IF(N27<>"",", "&N27,"")&IF(O27<>"",", "&O27,"")&IF(P27<>"",", "&P27,"")&IF(Q27<>"",", "&Q27,"")) -> h4, h13, h14, h8 | J27: Sus 4 indicadores (barras, tarjetas neto, QR, efectivo en caja) salen de estas historias; el efectivo en caja sale del arqueo (h8). | K27: {=IF(COUNTA(L27:Q27)=0,"OK (sin dependencias)",IF(SUMPRODUCT((L27:Q27<>"")*(COUNTIF($D$13:$D$29,L27:Q27)=0))>0,"ERROR: ID no existe",IF(MAX(IFERROR(INDEX($B$13:$B$29,MATCH(L27,$D$13:$D$29,0)),0),IFERROR(INDEX($B$13:$B$29,MATCH(M27,$D$13:$D$29,0)),0),IFERROR(INDEX($B$13:$B$29,MATCH(N27,$D$13:$D$29,0)),0),IFERROR(INDEX($B$13:$B$29,MATCH(O27,$D$13:$D$29,0)),0),IFERROR(INDEX($B$13:$B$29,MATCH(P27,$D$13:$D$29,0)),0),IFERROR(INDEX($B$13:$B$29,MATCH(Q27,$D$13:$D$29,0)),0))<B27,"OK","ERROR: depende de una historia posterior")))} -> OK | L27: h4 | M27: h13 | N27: h14 | O27: h8
B28: 16 | C28: {=INDEX('Pila de Producto (Backlog)'!$E$4:$E$20,MATCH($D28,'Pila de Producto (Backlog)'!$C$4:$C$20,0))} -> Cierre Seguro de Noche | D28: h18 | E28: Sprint 5 | F28: {=INDEX('Pila de Producto (Backlog)'!$J$4:$J$20,MATCH($D28,'Pila de Producto (Backlog)'!$C$4:$C$20,0))} -> Sprint 4 | G28: {=INDEX('Pila de Producto (Backlog)'!$H$4:$H$20,MATCH($D28,'Pila de Producto (Backlog)'!$C$4:$C$20,0))} -> 3 | H28: {=INDEX('Pila de Producto (Backlog)'!$I$4:$I$20,MATCH($D28,'Pila de Producto (Backlog)'!$C$4:$C$20,0))} -> 2.67 | I28: =IF(COUNTA(L28:Q28)=0,"—",L28&IF(M28<>"",", "&M28,"")&IF(N28<>"",", "&N28,"")&IF(O28<>"",", "&O28,"")&IF(P28<>"",", "&P28,"")&IF(Q28<>"",", "&Q28,"")) -> h2, h7, h8 | J28: Se sella la noche al final del flujo, cuando ya existen los datos que se quieren proteger (balance y arqueo). | K28: {=IF(COUNTA(L28:Q28)=0,"OK (sin dependencias)",IF(SUMPRODUCT((L28:Q28<>"")*(COUNTIF($D$13:$D$29,L28:Q28)=0))>0,"ERROR: ID no existe",IF(MAX(IFERROR(INDEX($B$13:$B$29,MATCH(L28,$D$13:$D$29,0)),0),IFERROR(INDEX($B$13:$B$29,MATCH(M28,$D$13:$D$29,0)),0),IFERROR(INDEX($B$13:$B$29,MATCH(N28,$D$13:$D$29,0)),0),IFERROR(INDEX($B$13:$B$29,MATCH(O28,$D$13:$D$29,0)),0),IFERROR(INDEX($B$13:$B$29,MATCH(P28,$D$13:$D$29,0)),0),IFERROR(INDEX($B$13:$B$29,MATCH(Q28,$D$13:$D$29,0)),0))<B28,"OK","ERROR: depende de una historia posterior")))} -> OK | L28: h2 | M28: h7 | N28: h8
B29: 17 | C29: {=INDEX('Pila de Producto (Backlog)'!$E$4:$E$20,MATCH($D29,'Pila de Producto (Backlog)'!$C$4:$C$20,0))} -> Vista Táctil Bodega | D29: h10 | E29: Sprint 2 | F29: {=INDEX('Pila de Producto (Backlog)'!$J$4:$J$20,MATCH($D29,'Pila de Producto (Backlog)'!$C$4:$C$20,0))} -> Sprint 4 | G29: {=INDEX('Pila de Producto (Backlog)'!$H$4:$H$20,MATCH($D29,'Pila de Producto (Backlog)'!$C$4:$C$20,0))} -> 8 | H29: {=INDEX('Pila de Producto (Backlog)'!$I$4:$I$20,MATCH($D29,'Pila de Producto (Backlog)'!$C$4:$C$20,0))} -> 0.63 | I29: =IF(COUNTA(L29:Q29)=0,"—",L29&IF(M29<>"",", "&M29,"")&IF(N29<>"",", "&N29,"")&IF(O29<>"",", "&O29,"")&IF(P29<>"",", "&P29,"")&IF(Q29<>"",", "&Q29,"")) -> h11 | J29: Vista alternativa para contar 30+ marcas en bodega. Ninguna historia depende de ella; va al final por su bajo ROI (0.63) y prioridad BAJA: si la velocidad no alcanza, se difiere sin afectar nada. | K29: {=IF(COUNTA(L29:Q29)=0,"OK (sin dependencias)",IF(SUMPRODUCT((L29:Q29<>"")*(COUNTIF($D$13:$D$29,L29:Q29)=0))>0,"ERROR: ID no existe",IF(MAX(IFERROR(INDEX($B$13:$B$29,MATCH(L29,$D$13:$D$29,0)),0),IFERROR(INDEX($B$13:$B$29,MATCH(M29,$D$13:$D$29,0)),0),IFERROR(INDEX($B$13:$B$29,MATCH(N29,$D$13:$D$29,0)),0),IFERROR(INDEX($B$13:$B$29,MATCH(O29,$D$13:$D$29,0)),0),IFERROR(INDEX($B$13:$B$29,MATCH(P29,$D$13:$D$29,0)),0),IFERROR(INDEX($B$13:$B$29,MATCH(Q29,$D$13:$D$29,0)),0))<B29,"OK","ERROR: depende de una historia posterior")))} -> OK | L29: h11
B31: ="Resultado de la validación: "&COUNTIF(K13:K29,"OK*")&" de "&COUNTA(D13:D29)&" historias sin errores de dependencia." -> Resultado de la validación: 17 de 17 historias sin errores de dependencia.
B33: Notas y supuestos:
B34: 1) Las dependencias se dedujeron del texto de cada historia; conviene confirmarlas con el equipo y con Don Ludo. Se editan en las columnas auxiliares L:Q y la validación se recalcula sola.
B35: 2) Cambio frente a la versión de 5 sprints: se fusionaron maestros+apertura con inventario inicial (Sprint 1) y configuración del turno con ventas en vivo (Sprint 2); liquidación y pagos quedan juntos (Sprint 3) y el balance final cierra el plan (Sprint 4). No se movió ninguna historia por delante de una dependencia.
B36: 3) Capacidad supuesta: ~20 puntos de historia por sprint (supuesto, no dato). La carga queda en 18, 20, 21 y 20; ajustar a la velocidad real. Si no alcanza, h10 (Vista Táctil Bodega) va al final de Sprint 4 y se difiere primero, porque nadie depende de ella.
B37: 4) h3 (Stock Inicial Barra) copia los saldos finales que produce h4 (conteo final), por eso va después de h4 (Sprint 3). El stock de apertura de la primera noche se fija con h12 (Despacho a Barras, Sprint 1).
B38: 5) h18 (Cierre Seguro de Noche) va después del balance (h7) y el arqueo (h8), para que el sellado proteja datos que ya existen.
B39: 6) Dependencias sin historia que las cubra (no se resuelven reordenando): (a) h7 y h8 hablan de 'gastos' como egreso, pero ninguna historia los registra; (b) h4 necesita definir productos y combos, y h11 un catálogo de marcas, sin historia propia; (c) no hay historia de roles/acceso (Administrador, Bartender, Cajero). Conviene crear historias nuevas, idealmente en Sprint 1.
B40: 7) ROI = Puntos Valor ÷ Puntos Historia (misma fórmula de v3). El ROI, los puntos y la prioridad se conservaron; dentro de cada sprint el orden respeta primero las dependencias y luego el ROI.

Sheet Sprint Backlog
B1: Metodologías ágiles: Lista de tareas de la iteración (Sprint Backlog)
B2: Historias de cada sprint en orden de ejecución. Tareas, voluntarios y horas los define el equipo en la Sprint Planning (según la plantilla); las columnas de burn-down Día 1–15 se agregan al iniciar cada sprint.
B4: Identificador (ID) de item de product backlog | C4: Enunciado del item de Product Backlog | D4: Tarea | E4: Dueño / Voluntario | F4: Estatus | G4: Horas estimadas totales
B5: ="Sprint 1 — Datos maestros, apertura de sesión e inventario inicial · "&'Plan de Sprints'!E4&" puntos de historia" -> Sprint 1 — Datos maestros, apertura de sesión e inventario inicial · 18 puntos de historia
B6: h2 | C6: {=INDEX('Pila de Producto (Backlog)'!$D$4:$D$20,MATCH(B6,'Pila de Producto (Backlog)'!$C$4:$C$20,0))} -> Como Administrador (Don Ludo), quiero abrir una nueva sesión nocturna seleccionando la fecha con detección automática del día de la semana, para habilitar las operaciones de venta y arqueo de la fecha. | D6: [Tareas por definir en Sprint Planning] | F6: Por iniciar
B7: h11 | C7: {=INDEX('Pila de Producto (Backlog)'!$D$4:$D$20,MATCH(B7,'Pila de Producto (Backlog)'!$C$4:$C$20,0))} -> Como Administrador, quiero modificar el stock de bodega con botones de pasos (-10, -1, +1, +10) o edición directa con guardado automático, para registrar entradas y mermas en segundos sin recargar la página. | D7: [Tareas por definir en Sprint Planning] | F7: Por iniciar
B8: h12 | C8: {=INDEX('Pila de Producto (Backlog)'!$D$4:$D$20,MATCH(B8,'Pila de Producto (Backlog)'!$C$4:$C$20,0))} -> Como Bartender o Administrador, quiero registrar las cajas y botellas que se suben de la bodega central a cada barra al inicio del turno, para fijar el stock de apertura por punto de despacho. | D8: [Tareas por definir en Sprint Planning] | F8: Por iniciar
B9: h15 | C9: {=INDEX('Pila de Producto (Backlog)'!$D$4:$D$20,MATCH(B9,'Pila de Producto (Backlog)'!$C$4:$C$20,0))} -> Como Administrador (Don Ludo), quiero gestionar la nómina de trabajadores con su nombre, celular, cargo normalizado (MESERO, BARTENDER, SEGURIDAD, LIMPIEZA) y jornal habitual, para tener la plantilla centralizada. | D9: [Tareas por definir en Sprint Planning] | F9: Por iniciar
B10: ="Sprint 2 — Configuración del turno y ventas en vivo · "&'Plan de Sprints'!E5&" puntos de historia" -> Sprint 2 — Configuración del turno y ventas en vivo · 20 puntos de historia
B11: h14 | C11: {=INDEX('Pila de Producto (Backlog)'!$D$4:$D$20,MATCH(B11,'Pila de Producto (Backlog)'!$C$4:$C$20,0))} -> Como Cajero o Mesero, quiero registrar cobros por QR seleccionando Yasta o Yape con sus logos oficiales e indicando el monto, para registrar transferencias bancarias de forma intuitiva. | D11: [Tareas por definir en Sprint Planning] | F11: Por iniciar
B12: h13 | C12: {=INDEX('Pila de Producto (Backlog)'!$D$4:$D$20,MATCH(B12,'Pila de Producto (Backlog)'!$C$4:$C$20,0))} -> Como Administrador (Don Ludo), quiero que al ingresar el voucher de tarjeta el sistema calcule la retención de la comisión del banco y el monto neto real que ingresa a la cuenta bancaria, para conocer la liquidez real. | D12: [Tareas por definir en Sprint Planning] | F12: Por iniciar
B13: h6 | C13: {=INDEX('Pila de Producto (Backlog)'!$D$4:$D$20,MATCH(B13,'Pila de Producto (Backlog)'!$C$4:$C$20,0))} -> Como Administrador, quiero que al abrir la noche se cargue automáticamente la nómina del personal programado para ese día con su jornal pactado, para liquidar los pagos del turno sin reescribir la lista. | D13: [Tareas por definir en Sprint Planning] | F13: Por iniciar
B14: h4 | C14: {=INDEX('Pila de Producto (Backlog)'!$D$4:$D$20,MATCH(B14,'Pila de Producto (Backlog)'!$C$4:$C$20,0))} -> Como Administrador, quiero registrar el conteo de botellas sobrantes al final de la noche en cada barra para que el sistema calcule automáticamente los combos vendidos y botellas extra, para determinar las ventas reales. | D14: [Tareas por definir en Sprint Planning] | F14: Por iniciar
B15: ="Sprint 3 — Liquidación, pagos y cierres operativos · "&'Plan de Sprints'!E6&" puntos de historia" -> Sprint 3 — Liquidación, pagos y cierres operativos · 21 puntos de historia
B16: h5 | C16: {=INDEX('Pila de Producto (Backlog)'!$D$4:$D$20,MATCH(B16,'Pila de Producto (Backlog)'!$C$4:$C$20,0))} -> Como Administrador (Don Ludo), quiero ver en un solo cuadro el total vendido en bebidas, lo cobrado por QR, lo tarjeteado y el efectivo neto que debe entregar cada bartender, para liquidar el turno sin diferencias. | D16: [Tareas por definir en Sprint Planning] | F16: Por iniciar
B17: h3 | C17: {=INDEX('Pila de Producto (Backlog)'!$D$4:$D$20,MATCH(B17,'Pila de Producto (Backlog)'!$C$4:$C$20,0))} -> Como Encargado de Barra, quiero sincronizar el inventario de apertura copiando automáticamente los saldos finales de la noche anterior, para no tener que recontar ni digitar de nuevo el stock base. | D17: [Tareas por definir en Sprint Planning] | F17: Por iniciar
B18: h16 | C18: {=INDEX('Pila de Producto (Backlog)'!$D$4:$D$20,MATCH(B18,'Pila de Producto (Backlog)'!$C$4:$C$20,0))} -> Como Administrador (Don Ludo), quiero marcar como pagado o editar el jornal de un trabajador con recálculo matemático inmediato de la planilla en el DOM, para pagar al personal en efectivo con rapidez. | D18: [Tareas por definir en Sprint Planning] | F18: Por iniciar
B19: h17 | C19: {=INDEX('Pila de Producto (Backlog)'!$D$4:$D$20,MATCH(B19,'Pila de Producto (Backlog)'!$C$4:$C$20,0))} -> Como Administrador, quiero pagar el jornal atrasado a un trabajador pulsando 'Pagar Jornal' con liquidación asincrónica instantánea, para saldar deudas de noches pasadas sin recargar la página. | D19: [Tareas por definir en Sprint Planning] | F19: Por iniciar
B20: ="Sprint 4 — Balance final, arqueo y dashboard · "&'Plan de Sprints'!E7&" puntos de historia" -> Sprint 4 — Balance final, arqueo y dashboard · 20 puntos de historia
B21: h7 | C21: {=INDEX('Pila de Producto (Backlog)'!$D$4:$D$20,MATCH(B21,'Pila de Producto (Backlog)'!$C$4:$C$20,0))} -> Como Administrador (Don Ludo), quiero visualizar en una sola pantalla sin scroll el balance total de ingresos (tarjetas, QRs, efectivo) frente a egresos (pagos y gastos), para hacer el arqueo en 10 segundos. | D21: [Tareas por definir en Sprint Planning] | F21: Por iniciar
B22: h8 | C22: {=INDEX('Pila de Producto (Backlog)'!$D$4:$D$20,MATCH(B22,'Pila de Producto (Backlog)'!$C$4:$C$20,0))} -> Como Administrador, quiero que el sistema calcule exactamente el dinero físico neto que debe haber en la caja fuerte o mano (Plata a Favor o Faltante), para comprobar el dinero antes de retirarme. | D22: [Tareas por definir en Sprint Planning] | F22: Por iniciar
B23: h9 | C23: {=INDEX('Pila de Producto (Backlog)'!$D$4:$D$20,MATCH(B23,'Pila de Producto (Backlog)'!$C$4:$C$20,0))} -> Como Administrador (Don Ludo), quiero consultar un Dashboard con los 4 indicadores esenciales (Venta en Barras, Tarjetas Neto Banco, Cobros QR y Efectivo en Caja) alimentados 100% por datos reales, para conocer la marcha del negocio de un vistazo. | D23: [Tareas por definir en Sprint Planning] | F23: Por iniciar
B24: h18 | C24: {=INDEX('Pila de Producto (Backlog)'!$D$4:$D$20,MATCH(B24,'Pila de Producto (Backlog)'!$C$4:$C$20,0))} -> Como Administrador (Don Ludo), quiero sellar la noche con un botón de cierre seguro que bloquee ediciones accidentales, con facultad de reabrirla si se requiere corregir algún dato. | D24: [Tareas por definir en Sprint Planning] | F24: Por iniciar
B25: h10 | C25: {=INDEX('Pila de Producto (Backlog)'!$D$4:$D$20,MATCH(B25,'Pila de Producto (Backlog)'!$C$4:$C$20,0))} -> Como Administrador de Bodega, quiero alternar entre una vista de Tabla Ejecutiva y una Cuadrícula de Tarjetas táctiles, para agilizar tanto el conteo rápido de más de 30 marcas como la auditoría visual. | D25: [Tareas por definir en Sprint Planning] | F25: Por iniciar
